{
    "namespace": "cluster",
    "service_name": "tx_gateway",
    "includes": [
        "cluster/types.h"
    ],
    "methods": [
        {
            "name": "begin_tx",
            "input_type": "begin_tx_request",
            "output_type": "begin_tx_reply"
        },
        {
            "name": "prepare_tx",
            "input_type": "prepare_tx_request",
            "output_type": "prepare_tx_reply"
        },
        {
            "name": "commit_tx",
            "input_type": "commit_tx_request",
            "output_type": "commit_tx_reply"
        },
        {
            "name": "abort_tx",
            "input_type": "abort_tx_request",
            "output_type": "abort_tx_reply"
        },
        {
            "name": "ping_tm",
            "input_type": "ping_tm_request",
            "output_type": "ping_tm_reply"
        }
    ]
}
